podlozhnyy_module/__init__.py
podlozhnyy_module/abtesting.py
podlozhnyy_module/anova.py
podlozhnyy_module/bootstrap.py
podlozhnyy_module/charts.py
podlozhnyy_module/collocation.py
podlozhnyy_module/correlation.py
podlozhnyy_module/pareto.py
podlozhnyy_module/permutation.py
podlozhnyy_module/regression.py
podlozhnyy_module/timeseries.py
podlozhnyy_module/timetest.py
podlozhnyy_module-2.5.3.dist-info/METADATA
podlozhnyy_module-2.5.3.dist-info/WHEEL
podlozhnyy_module-2.5.3.dist-info/top_level.txt
podlozhnyy_module-2.5.3.dist-info/RECORD
