Metadata-Version: 2.1
Name: podlozhnyy-module
Version: 2.5.3
Summary: One place for the most useful methods for work
Home-page: https://github.com/NPodlozhniy/podlozhnyy-module
Author: Nikita Podlozhnyy
Author-email: podlozhnyy.ne@phystech.edu
License: MIT
Platform: UNKNOWN
Classifier: Development Status :: 3 - Alpha
Classifier: License :: OSI Approved :: MIT License
Classifier: Programming Language :: Python
Classifier: Programming Language :: Python :: 3
Classifier: Programming Language :: Python :: 3.7
Requires-Python: >=3.7.0
Requires-Dist: scikit-learn (>=0.24.2)
Requires-Dist: statsmodels (>=0.12.2)
Requires-Dist: numpy (>=1.20.3)
Requires-Dist: pandas (>=1.2.4)
Requires-Dist: seaborn (>=0.11.1)
Requires-Dist: holoviews (>=1.14.3)
Requires-Dist: matplotlib (>=3.4.2)
Requires-Dist: scipy (>=1.6.3)
Requires-Dist: nltk (>=3.6.2)
